{
  "schema_version": "cockpit-public/v1",
  "generated_at": "2026-07-16T00:49:44Z",
  "meta": {
    "as_of_date": "2026-07-15",
    "coverage_status": "PASS",
    "source_rule_run_id": "deb78c1e-fb82-469f-9e34-aee5abdd060b",
    "source_ingest_run_id": "5eaa1b1b-3580-494b-81ae-033730377ad7",
    "snapshot_generated_at": "2026-07-16T00:47:57Z",
    "warnings": []
  },
  "market_gate_on": false,
  "market_caution": {
    "schema_version": "market-caution/v3",
    "as_of_date": "2026-07-15",
    "score": 65.4,
    "tier": "elevated",
    "fires": false,
    "fire_threshold": 80,
    "elevated_threshold": 60,
    "components": {
      "c1z": 0.466,
      "qqq_close_location": 0.064,
      "supz": -0.32,
      "flow_z": -0.533,
      "flow_mom": 0.0076,
      "c1_warn_pct": 78.26
    },
    "rule": "composite SCORE = 100*P(risk_off<=20d) from logistic(c1z,neg_cloc,supz,neg_flowz,flow_mom); fires when score>=80",
    "scope": "display-only caution — objective is caution->risk_off (NOT deep-drawdown); does NOT gate entry/verdict/BUY/EXIT",
    "evidence": "AUC det20 test=0.65 vs dd8 test=0.52; at score>=80 precision~0.65 recall~0.22 (base 0.40)",
    "model_fit_as_of": "2026-06-09"
  },
  "caution_history": [
    62.3,
    53.6,
    69.8,
    67.4,
    57.1,
    68.4,
    69.1,
    57.4,
    53.6,
    67.3,
    57.8,
    65.4
  ],
  "caution_sessions": 12,
  "counts": {
    "entry": 0,
    "continuation": 2
  },
  "entry": [],
  "continuation": [
    {
      "ticker": "ETSY",
      "company_name": "Etsy",
      "verdict": "WATCH",
      "verdict_sub": "weak",
      "phase": "STRONG_UPTREND",
      "layer": "control_growth_internet",
      "setup_text": "vol20=1.29|tr20=1.68|cloc=0.73|zone=range_high|confirmed_above_zone",
      "setup_tokens": [
        "HOLD"
      ],
      "rank": null,
      "score": null,
      "score_trend": null,
      "score_short": null,
      "c1": {
        "c15_prob": 0.262759,
        "c15_prob_raw": 0.281785,
        "confidence": "medium",
        "n_features": 27
      },
      "ddr": {
        "ddr_5d_5pct": 0.43902439024390244,
        "ddr_confidence": "high",
        "ddr_n_bucket": 41,
        "ddr_overheat": 0.6862097440132122,
        "dd_profile_as_of_date": "2026-07-15",
        "dd_current_pct": 0.0,
        "dd_to_median_pct": -0.15126898690257734,
        "dd_median_pct": 0.15126898690257734,
        "dd_p25_pct": 0.12700476726047535,
        "dd_p75_pct": 0.17593588939694838,
        "dd_worst_pct": 0.21053520930457725,
        "dd_best_pct": 0.0797031151562642,
        "dd_sample_size": 10,
        "dd_confidence": "high",
        "dd_coverage_status": "FULL_10Y",
        "dd_p_break_median": 0.5384615384615384,
        "dd_n_pullbacks_median": 13,
        "dd_n_breaks_median": 7,
        "dd_current_cycle_peak_date": "2026-07-15",
        "dd_current_cycle_peak_price": 85.73999786376953,
        "dd_day_streak": 62,
        "dd_current_gain_pct": 0.43834921969251534
      },
      "stop_ref": "2ATR 79.17 (+8.3%)",
      "zone_low": 80.89576843806675,
      "zone_high": 83.36000061035156,
      "zone_label": "range_high",
      "target_zone": null,
      "exit_action": "No exit signal",
      "exit_signal": "EXIT_0_HOLD",
      "supply": "CONFIRM",
      "supply_action": "ALLOW/HOLD",
      "flow": "STRONG_INFLOW",
      "money_flow_score": null,
      "age_bars": 1,
      "why_waiting": "No qualifying BUY setup or fresh phase-up transition",
      "buy_quality": "",
      "buy_signal": "",
      "buy_source": null,
      "price": null,
      "price_date": null
    },
    {
      "ticker": "BILL",
      "company_name": "BILL Holdings",
      "verdict": "WATCH",
      "verdict_sub": "weak",
      "phase": "ACCUMULATION",
      "layer": "control_growth_software",
      "setup_text": "vol20=1.41|tr20=2.03|cloc=0.87|zone=range_high|confirmed_above_zone",
      "setup_tokens": [
        "HOLD"
      ],
      "rank": null,
      "score": null,
      "score_trend": null,
      "score_short": null,
      "c1": {
        "c15_prob": 0.398374,
        "c15_prob_raw": 0.374045,
        "confidence": "high",
        "n_features": 27
      },
      "ddr": {
        "ddr_5d_5pct": null,
        "ddr_confidence": null,
        "ddr_n_bucket": null,
        "ddr_overheat": null,
        "dd_profile_as_of_date": "2026-07-15",
        "dd_current_pct": null,
        "dd_to_median_pct": null,
        "dd_median_pct": 0.16349890380431023,
        "dd_p25_pct": 0.14912932465110665,
        "dd_p75_pct": 0.1794250041194182,
        "dd_worst_pct": 0.36218048729750113,
        "dd_best_pct": 0.10122537069663579,
        "dd_sample_size": 5,
        "dd_confidence": "high",
        "dd_coverage_status": "PARTIAL_LISTING_HISTORY",
        "dd_p_break_median": 0.4,
        "dd_n_pullbacks_median": 10,
        "dd_n_breaks_median": 4,
        "dd_current_cycle_peak_date": null,
        "dd_current_cycle_peak_price": null,
        "dd_day_streak": null,
        "dd_current_gain_pct": null
      },
      "stop_ref": "2ATR 40.67 (+9.7%)",
      "zone_low": 42.08510650907244,
      "zone_high": 43.56999969482422,
      "zone_label": "range_high",
      "target_zone": null,
      "exit_action": "No exit signal",
      "exit_signal": "EXIT_0_HOLD",
      "supply": "CONFIRM",
      "supply_action": "ALLOW/HOLD",
      "flow": "STRONG_INFLOW",
      "money_flow_score": null,
      "age_bars": 44,
      "why_waiting": "No qualifying BUY setup or fresh phase-up transition",
      "buy_quality": "",
      "buy_signal": "",
      "buy_source": null,
      "price": null,
      "price_date": null
    }
  ],
  "momentum": {
    "leaders": [
      {
        "ticker": "LITE",
        "rs_pctl": 100,
        "top_decile": true,
        "is_entry": false,
        "risk_flags": [],
        "snapshot_clean": false
      },
      {
        "ticker": "WDC",
        "rs_pctl": 100,
        "top_decile": true,
        "is_entry": false,
        "risk_flags": [],
        "snapshot_clean": false
      },
      {
        "ticker": "MU",
        "rs_pctl": 99,
        "top_decile": true,
        "is_entry": false,
        "risk_flags": [],
        "snapshot_clean": false
      },
      {
        "ticker": "AEHR",
        "rs_pctl": 99,
        "top_decile": true,
        "is_entry": false,
        "risk_flags": [],
        "snapshot_clean": false
      },
      {
        "ticker": "STX",
        "rs_pctl": 98,
        "top_decile": true,
        "is_entry": false,
        "risk_flags": [],
        "snapshot_clean": false
      },
      {
        "ticker": "CIEN",
        "rs_pctl": 98,
        "top_decile": true,
        "is_entry": false,
        "risk_flags": [],
        "snapshot_clean": false
      },
      {
        "ticker": "LWLG",
        "rs_pctl": 98,
        "top_decile": true,
        "is_entry": false,
        "risk_flags": [],
        "snapshot_clean": false
      },
      {
        "ticker": "INTC",
        "rs_pctl": 97,
        "top_decile": true,
        "is_entry": false,
        "risk_flags": [],
        "snapshot_clean": false
      },
      {
        "ticker": "DOCN",
        "rs_pctl": 97,
        "top_decile": true,
        "is_entry": false,
        "risk_flags": [],
        "snapshot_clean": false
      },
      {
        "ticker": "UCTT",
        "rs_pctl": 96,
        "top_decile": true,
        "is_entry": false,
        "risk_flags": [],
        "snapshot_clean": false
      },
      {
        "ticker": "ICHR",
        "rs_pctl": 96,
        "top_decile": true,
        "is_entry": false,
        "risk_flags": [],
        "snapshot_clean": false
      },
      {
        "ticker": "VIAV",
        "rs_pctl": 96,
        "top_decile": true,
        "is_entry": false,
        "risk_flags": [],
        "snapshot_clean": false
      },
      {
        "ticker": "ALAB",
        "rs_pctl": 95,
        "top_decile": true,
        "is_entry": false,
        "risk_flags": [],
        "snapshot_clean": false
      },
      {
        "ticker": "AMD",
        "rs_pctl": 95,
        "top_decile": true,
        "is_entry": false,
        "risk_flags": [],
        "snapshot_clean": false
      }
    ],
    "coverage": [
      249,
      250
    ],
    "limit": 14,
    "decile_n": 25
  }
}